HErmes/__init__.py
HErmes/analysis/__init__.py
HErmes/analysis/calculus.py
HErmes/analysis/fluxes.py
HErmes/analysis/tasks.py
HErmes/fitting/__init__.py
HErmes/fitting/fit.py
HErmes/fitting/functions.py
HErmes/fitting/model.py
HErmes/selection/__init__.py
HErmes/selection/categories.py
HErmes/selection/cut.py
HErmes/selection/dataset.py
HErmes/selection/magic_keywords.py
HErmes/selection/variables.py
HErmes/utils/PATTERNS.cfg
HErmes/utils/__init__.py
HErmes/utils/files.py
HErmes/visual/__init__.py
HErmes/visual/canvases.py
HErmes/visual/plotting.py
HErmes_py-0.2.0.dist-info/LICENSE
HErmes_py-0.2.0.dist-info/METADATA
HErmes_py-0.2.0.dist-info/WHEEL
HErmes_py-0.2.0.dist-info/top_level.txt
HErmes_py-0.2.0.dist-info/RECORD
